broom.py
broom-0.0.1.dist-info/METADATA
broom-0.0.1.dist-info/RECORD
broom-0.0.1.dist-info/WHEEL
broom-0.0.1.dist-info/entry_points.txt
broom-0.0.1.dist-info/top_level.txt
