Metadata-Version: 2.1
Name: broom
Version: 0.0.1
Summary: Keep your desktop clutter-free.
Home-page: https://github.com/umluizlima/broom
Author: Luiz Lima
Author-email: umluizlima@gmail.com
License: MIT License
Platform: UNKNOWN
Classifier: Programming Language :: Python :: 3
Classifier: License :: OSI Approved :: MIT License
Classifier: Operating System :: OS Independent
